README.rst
setup.py
StrictConf.egg-info/PKG-INFO
StrictConf.egg-info/SOURCES.txt
StrictConf.egg-info/dependency_links.txt
StrictConf.egg-info/top_level.txt
strictconf/__init__.py
strictconf/checker.py
strictconf/compat.py
strictconf/compose.py
strictconf/config.py
strictconf/data.py
strictconf/toml.py
strictconf/yaml.py