Metadata-Version: 1.0
Name: StrictConf
Version: 0.2.0
Summary: Configuration library with type-checking
Home-page: https://github.com/vmagamedov/strictconf
Author: Vladimir Magamedov
Author-email: vladimir@magamedov.com
License: BSD
Platform: UNKNOWN
